sarand/__init__.py
sarand/__main__.py
sarand/amr_neighborhood_in_contigs.py
sarand/annotation_visualization.py
sarand/config.py
sarand/extract_neighborhood.py
sarand/full_pipeline.py
sarand/new_extract_neighborhood.py
sarand/test_metacherchant.py
sarand/utils.py
sarand/data/CARD_AMR_seq.fasta
sarand/external/__init__.py
sarand/external/bakta.py
sarand/external/bandage.py
sarand/external/blastn.py
sarand/external/graph_aligner.py
sarand/external/rgi.py
sarand/model/__init__.py
sarand/model/fasta_seq.py
sarand/model/graph_alignment_output.py
sarand/util/__init__.py
sarand/util/file.py
sarand/util/logger.py
sarand/util/pkg.py
sarand-1.1.1.dist-info/licenses/LICENSE.txt
sarand-1.1.1.dist-info/METADATA
sarand-1.1.1.dist-info/WHEEL
sarand-1.1.1.dist-info/entry_points.txt
sarand-1.1.1.dist-info/top_level.txt
sarand-1.1.1.dist-info/zip-safe
sarand-1.1.1.dist-info/RECORD
