Metadata-Version: 2.4
Name: sarand
Version: 1.1.1
Summary: Tool to extract the neighborhood of the target Antimicrobial Resistance (AMR) genes from the assembly graph.
Home-page: https://github.com/beiko-lab/sarand
Author: Somayeh Kafaie
Author-email: so.kafaie@gmail.com
License: GPLv3
Keywords: Metagenomic Assembly graph,Antimicrobial resistance,Context extraction
Classifier: Development Status :: 4 - Beta
Classifier: Environment :: Console
Classifier: License :: OSI Approved :: GNU General Public License v3 (GPLv3)
Classifier: Natural Language :: English
Classifier: Operating System :: MacOS
Classifier: Operating System :: POSIX
Classifier: Operating System :: POSIX :: Linux
Classifier: Programming Language :: Python :: 3
Classifier: Programming Language :: Python :: 3.7
Classifier: Programming Language :: Python :: 3.8
Classifier: Programming Language :: Python :: 3.9
Classifier: Intended Audience :: Science/Research
Classifier: Intended Audience :: Healthcare Industry
Classifier: Topic :: Scientific/Engineering :: Bio-Informatics
Requires-Python: >=3.7
License-File: LICENSE.txt
Requires-Dist: dna_features_viewer
Requires-Dist: numpy
Requires-Dist: pillow
Requires-Dist: matplotlib
Requires-Dist: gfapy
Requires-Dist: pandas
Requires-Dist: biopython
Dynamic: author
Dynamic: author-email
Dynamic: classifier
Dynamic: description
Dynamic: description-content-type
Dynamic: home-page
Dynamic: keywords
Dynamic: license
Dynamic: license-file
Dynamic: requires-dist
Dynamic: requires-python
Dynamic: summary
